CHANGELOG.txt
LICENCE.txt
MANIFEST.in
README.txt
setup.py
basic_func.egg-info/PKG-INFO
basic_func.egg-info/SOURCES.txt
basic_func.egg-info/dependency_links.txt
basic_func.egg-info/top_level.txt
source/__init__.py