Metadata-Version: 1.1
Name: basic-func
Version: 0.0.1
Summary: A bunch of basic functions needed for all Python programs
Home-page: UNKNOWN
Author: Shanvanth Arunmozhi
Author-email: shanvantharunmozhi@gmail.com
License: MIT
Keywords: functions
Platform: UNKNOWN
Classifier: Development Status :: 5 - Production/Stable
Classifier: Intended Audience :: Education
Classifier: Operating System :: Microsoft :: Windows :: Windows 10
Classifier: License :: OSI Approved :: MIT License
Classifier: Programming Language :: Python :: 3
